mcqq_tool/__init__.py
mcqq_tool/bg.png
mcqq_tool/config.py
mcqq_tool/draw_result.py
mcqq_tool/model.py
mcqq_tool/parse_qq_msg.py
mcqq_tool/rule.py
mcqq_tool/send_to_mc.py
mcqq_tool/send_to_qq.py
mcqq_tool/unifont-15.0.01.ttf
mcqq_tool/utils.py
mcqq_tool-1.3.4.post1.dist-info/LICENSE
mcqq_tool-1.3.4.post1.dist-info/METADATA
mcqq_tool-1.3.4.post1.dist-info/WHEEL
mcqq_tool-1.3.4.post1.dist-info/RECORD
