Metadata-Version: 2.1
Name: mcqq-tool
Version: 1.3.4.post1
Summary: MC_QQ工具包
License: MIT
Author: 17TheWord
Author-email: 17theword@gmail.com
Requires-Python: >=3.9,<4.0
Classifier: License :: OSI Approved :: MIT License
Classifier: Programming Language :: Python :: 3
Classifier: Programming Language :: Python :: 3.9
Classifier: Programming Language :: Python :: 3.10
Classifier: Programming Language :: Python :: 3.11
Classifier: Programming Language :: Python :: 3.12
Classifier: Programming Language :: Python :: 3.13
Requires-Dist: nonebot-adapter-minecraft (>=1.3.2.post1,<2.0.0)
Requires-Dist: nonebot-adapter-onebot (>=2.4.4,<3.0.0)
Requires-Dist: nonebot-adapter-qq (>=1.5.1,<2.0.0)
Requires-Dist: nonebot-plugin-guild-patch-remix (>=0.2.4,<0.3.0)
Requires-Dist: nonebot2 (>=2.3.3,<3.0.0)
